[
    { "path": "index.html", "type": "link" },
    { "path": "fluffy-timer.html", "type": "link" },
    { "path": "career.html", "type": "link" },
    { "path": "blog.html", "type": "link" },
    { "path": "contact.html", "type": "link" },
    { "path": "404.html", "type": "link" },

    { "path": "favicon.ico", "type": "external-image" },

    { "path": "res/fonts/edlo.ttf", "type": "external" },

    { "path": "res/css/layout.css", "type": "external" },
    { "path": "res/css/syntax-dark.css", "type": "external" },
    { "path": "res/css/syntax-light.css", "type": "external" },

    { "path": "res/css/components/card.css", "type": "external" },
    { "path": "res/css/components/loading.css", "type": "external" },
    { "path": "res/css/components/terminal.css", "type": "external" },
    { "path": "res/css/pages/blog.css", "type": "external" },
    { "path": "res/css/pages/index.css", "type": "external" },
    { "path": "res/css/pages/fluffy-timer.css", "type": "external" },
    { "path": "res/css/pages/404.css", "type": "external" },
    { "path": "res/css/page-layouts/centered-component.css", "type": "external" },
    { "path": "res/css/page-layouts/centered-component.css", "type": "external" },

    { "path": "res/data/files.json", "type": "external" },
    { "path": "res/data/blog_posts.json", "type": "external" },

    { "path": "res/favicon/android-chrome-192x192.png", "type": "external-image" },
    { "path": "res/favicon/android-chrome-512x512.png", "type": "external-image" },
    { "path": "res/favicon/apple-touch-icon.png", "type": "external-image" },
    { "path": "res/favicon/favicon-16x16.png", "type": "external-image" },
    { "path": "res/favicon/favicon-32x32.png", "type": "external-image" },

    { "path": "res/img/404.png", "type": "external-image" },
    { "path": "res/img/engineercoding_github_io.jpg", "type": "external-image" },
    { "path": "res/img/index.png", "type": "external-image" },

    { "path": "res/js/blog.js", "type": "external" },
    { "path": "res/js/generic.js", "type": "external" },
    { "path": "res/js/nav.js", "type": "external" },
    { "path": "res/js/template-loader.js", "type": "external" },
    { "path": "res/js/terminal.js", "type": "external" },
    { "path": "res/js/theme-switcher.js", "type": "external" }
]
